clickbait_commit_messages/__init__.py
clickbait_commit_messages/providers/__init__.py
clickbait_commit_messages/providers/base.py
clickbait_commit_messages/providers/errors.py
clickbait_commit_messages/providers/groq.py
clickbait_commit_messages/providers/huggingface.py
list_available_models.py
make_clickbaity.py
clickbait_commit_messages-1.0.0.dist-info/LICENSE
clickbait_commit_messages-1.0.0.dist-info/METADATA
clickbait_commit_messages-1.0.0.dist-info/WHEEL
clickbait_commit_messages-1.0.0.dist-info/entry_points.txt
clickbait_commit_messages-1.0.0.dist-info/RECORD
