Metadata-Version: 2.1
Name: clickbait-commit-messages
Version: 1.0.0
Summary: Make your commit messages extremely catchy.
License: MIT
Author: anferico
Author-email: f.cariaggi4@gmail.com
Requires-Python: >=3.9,<4.0
Classifier: License :: OSI Approved :: MIT License
Classifier: Programming Language :: Python :: 3
Classifier: Programming Language :: Python :: 3.9
Classifier: Programming Language :: Python :: 3.10
Classifier: Programming Language :: Python :: 3.11
Requires-Dist: groq (>=0.5.0,<0.6.0)
Requires-Dist: huggingface-hub[inference] (>=0.22.2,<0.23.0)
Requires-Dist: requests (>=2.31.0,<3.0.0)
